physox/__init__.py
physox/collisions.py
physox/constants.py
physox/dynamics.py
physox/electromagnetism.py
physox/energy.py
physox/gravity.py
physox/kinematics.py
physox/matter.py
physox/momentum.py
physox/probability.py
physox/rotation.py
physox/thermo.py
physox/waves.py
physox-0.1.0.dist-info/licenses/LICENSE
physox-0.1.0.dist-info/METADATA
physox-0.1.0.dist-info/WHEEL
physox-0.1.0.dist-info/top_level.txt
physox-0.1.0.dist-info/RECORD
