Metadata-Version: 2.4
Name: physox
Version: 0.1.0
Summary: PhysOx — physics utilities in voxel and tick space
Author-email: "Dr. Ippy" <admin@jdplumbingsoflo.com>
License:                                  Apache License
Project-URL: Homepage, https://github.com/JDPlumbing/physox
Project-URL: Repository, https://github.com/JDPlumbing/physox
Keywords: physics,simulation,voxel,time,space
Classifier: Programming Language :: Python :: 3
Classifier: License :: OSI Approved :: Apache Software License
Classifier: Operating System :: OS Independent
Classifier: Intended Audience :: Science/Research
Classifier: Topic :: Scientific/Engineering
Requires-Python: >=3.9
License-File: LICENSE
Dynamic: license-file
